{
  "5475799363": {
    "gameID": "5475799363",
    "gameResult": "win",
    "GameType": "Ranked Solo",
    "gameTime_string": "2021-09-25 22:24:12",
    "GameLength": "27m 7s",
    "kill": "14",
    "Death": "3",
    "Assist": "10",
    "KDARatio": "8.00:1",
    "Badge1": "MVP",
    "Badge2": "empty",
    "champion": "Zed",
    "Tier_Average": "Diamond 1",
    "Control_Ward": "empty",
    "teammate_champion0": "Lee Sin",
    "teammate_id0": "무조건 탑 동선",
    "teammate_champion1": "Gragas",
    "teammate_id1": "나도 끠즤",
    "teammate_champion2": "Irelia",
    "teammate_id2": "코 태",
    "teammate_champion3": "Samira",
    "teammate_id3": "na li dou shi ni",
    "teammate_champion4": "Rell",
    "teammate_id4": "cleannn",
    "enermy_champion0": "Fiora",
    "enermy_id0": "TOPKING",
    "enermy_champion1": "Zed",
    "enermy_id1": "Ma1ibu night",
    "enermy_champion2": "Neeko",
    "enermy_id2": "nkeeo",
    "enermy_champion3": "Aphelios",
    "enermy_id3": "게으른 연습벌레",
    "enermy_champion4": "Lulu",
    "enermy_id4": "AlwaysSorryTool"
  },
  "5475669285": {
    "gameID": "5475669285",
    "gameResult": "lose",
    "GameType": "Ranked Solo",
    "gameTime_string": "2021-09-25 21:43:05",
    "GameLength": "28m 54s",
    "kill": "6",
    "Death": "7",
    "Assist": "7",
    "KDARatio": "1.86:1",
    "Badge1": "ACE",
    "Badge2": "empty",
    "champion": "Nidalee",
    "Tier_Average": "Master",
    "Control_Ward": "empty",
    "teammate_champion0": "Vayne",
    "teammate_id0": "북극곰 아프다",
    "teammate_champion1": "Karthus",
    "teammate_id1": "언젠가의 이야기",
    "teammate_champion2": "Yone",
    "teammate_id2": "Leminem",
    "teammate_champion3": "Jhin",
    "teammate_id3": "beican shenghuo",
    "teammate_champion4": "Leona",
    "teammate_id4": "응애응애1212",
    "enermy_champion0": "Sylas",
    "enermy_id0": "TOPKING",
    "enermy_champion1": "Nidalee",
    "enermy_id1": "Ma1ibu night",
    "enermy_champion2": "Riven",
    "enermy_id2": "씨야보람",
    "enermy_champion3": "Miss Fortune",
    "enermy_id3": "gkatjrgs",
    "enermy_champion4": "Alistar",
    "enermy_id4": "미드 사용법12"
  },
  "5475681866": {
    "gameID": "5475681866",
    "gameResult": "win",
    "GameType": "Ranked Solo",
    "gameTime_string": "2021-09-25 21:03:19",
    "GameLength": "19m 34s",
    "kill": "15",
    "Death": "1",
    "Assist": "8",
    "KDARatio": "23.00:1",
    "Badge1": "Double Kill",
    "Badge2": "MVP",
    "champion": "Lee Sin",
    "Tier_Average": "Master",
    "Control_Ward": "empty",
    "teammate_champion0": "Yasuo",
    "teammate_id0": "Leminem",
    "teammate_champion1": "Lillia",
    "teammate_id1": "언젠가의 이야기",
    "teammate_champion2": "Ziggs",
    "teammate_id2": "heize fans",
    "teammate_champion3": "Lucian",
    "teammate_id3": "전 모르겠어요",
    "teammate_champion4": "Bard",
    "teammate_id4": "I HAVE N0 IDEA",
    "enermy_champion0": "Jayce",
    "enermy_id0": "TOPKING",
    "enermy_champion1": "Lee Sin",
    "enermy_id1": "Ma1ibu night",
    "enermy_champion2": "Zoe",
    "enermy_id2": "Is Y0u Down",
    "enermy_champion3": "Xayah",
    "enermy_id3": "모두다일어나",
    "enermy_champion4": "Yuumi",
    "enermy_id4": "102b"
  },
  "5475573219": {
    "gameID": "5475573219",
    "gameResult": "win",
    "GameType": "Ranked Solo",
    "gameTime_string": "2021-09-25 20:23:37",
    "GameLength": "18m 25s",
    "kill": "9",
    "Death": "1",
    "Assist": "7",
    "KDARatio": "16.00:1",
    "Badge1": "Triple Kill",
    "Badge2": "empty",
    "champion": "Taliyah",
    "Tier_Average": "Master",
    "Control_Ward": "empty",
    "teammate_champion0": "Irelia",
    "teammate_id0": "who is niuma",
    "teammate_champion1": "Taliyah",
    "teammate_id1": "Ma1ibu night",
    "teammate_champion2": "Lucian",
    "teammate_id2": "TOPKING",
    "teammate_champion3": "Ezreal",
    "teammate_id3": "순수하지",
    "teammate_champion4": "Trundle",
    "teammate_id4": "예진님 짱",
    "enermy_champion0": "Jayce",
    "enermy_id0": "AWM gtr",
    "enermy_champion1": "Nidalee",
    "enermy_id1": "0909dedie",
    "enermy_champion2": "Sylas",
    "enermy_id2": "헌  언",
    "enermy_champion3": "Kalista",
    "enermy_id3": "T10 Berserker",
    "enermy_champion4": "Thresh",
    "enermy_id4": "라윤공주"
  },
  "5474214007": {
    "gameID": "5474214007",
    "gameResult": "win",
    "GameType": "URF",
    "gameTime_string": "2021-09-25 03:57:33",
    "GameLength": "13m 32s",
    "kill": "12",
    "Death": "7",
    "Assist": "12",
    "KDARatio": "3.43:1",
    "Badge1": "Double Kill",
    "Badge2": "empty",
    "champion": "Jayce",
    "Tier_Average": "empty",
    "Control_Ward": "empty",
    "teammate_champion0": "Udyr",
    "teammate_id0": "퓨어블랙",
    "teammate_champion1": "Jayce",
    "teammate_id1": "새콤달콤 자몽맛",
    "teammate_champion2": "Morgana",
    "teammate_id2": "최경렬",
    "teammate_champion3": "Jinx",
    "teammate_id3": "본캐티어 아이언",
    "teammate_champion4": "Aatrox",
    "teammate_id4": "카why네",
    "enermy_champion0": "Ekko",
    "enermy_id0": "파풀러",
    "enermy_champion1": "Jayce",
    "enermy_id1": "Ma1ibu night",
    "enermy_champion2": "Kayn",
    "enermy_id2": "묵언수행고인물",
    "enermy_champion3": "Fizz",
    "enermy_id3": "TOPKING",
    "enermy_champion4": "Zed",
    "enermy_id4": "람쥐썬더7777"
  },
  "5474089886": {
    "gameID": "5474089886",
    "gameResult": "win",
    "GameType": "Ranked Solo",
    "gameTime_string": "2021-09-25 03:30:17",
    "GameLength": "24m 5s",
    "kill": "6",
    "Death": "3",
    "Assist": "7",
    "KDARatio": "4.33:1",
    "Badge1": "Double Kill",
    "Badge2": "empty",
    "champion": "Talon",
    "Tier_Average": "Diamond 1",
    "Control_Ward": "empty",
    "teammate_champion0": "Sett",
    "teammate_id0": "98kfrf",
    "teammate_champion1": "Graves",
    "teammate_id1": "yon gan niu niu",
    "teammate_champion2": "Katarina",
    "teammate_id2": "큐즈익스",
    "teammate_champion3": "Twitch",
    "teammate_id3": "no voy",
    "teammate_champion4": "Thresh",
    "teammate_id4": "lIllllIlII",
    "enermy_champion0": "Camille",
    "enermy_id0": "TOPKING",
    "enermy_champion1": "Talon",
    "enermy_id1": "Ma1ibu night",
    "enermy_champion2": "LeBlanc",
    "enermy_id2": "The Battle Cats",
    "enermy_champion3": "Draven",
    "enermy_id3": "Dgdb",
    "enermy_champion4": "Leona",
    "enermy_id4": "미아에몽"
  },
  "5474008326": {
    "gameID": "5474008326",
    "gameResult": "win",
    "GameType": "Ranked Solo",
    "gameTime_string": "2021-09-25 02:51:12",
    "GameLength": "16m 47s",
    "kill": "5",
    "Death": "0",
    "Assist": "9",
    "KDARatio": "Perfect",
    "Badge1": "MVP",
    "Badge2": "empty",
    "champion": "Jarvan IV",
    "Tier_Average": "Master",
    "Control_Ward": "empty",
    "teammate_champion0": "Jayce",
    "teammate_id0": "TOPKING",
    "teammate_champion1": "Jarvan IV",
    "teammate_id1": "Ma1ibu night",
    "teammate_champion2": "Sylas",
    "teammate_id2": "평화로운 행동대장 에그타르트",
    "teammate_champion3": "Lucian",
    "teammate_id3": "혜지명1",
    "teammate_champion4": "Soraka",
    "teammate_id4": "허니아",
    "enermy_champion0": "Urgot",
    "enermy_id0": "탑 우르 곳감",
    "enermy_champion1": "Taliyah",
    "enermy_id1": "밀림 간 다",
    "enermy_champion2": "Irelia",
    "enermy_id2": "함구무언1",
    "enermy_champion3": "Xayah",
    "enermy_id3": "아 나이뜨",
    "enermy_champion4": "Rakan",
    "enermy_id4": "김은지전용노예"
  },
  "5474003060": {
    "gameID": "5474003060",
    "gameResult": "lose",
    "GameType": "Ranked Solo",
    "gameTime_string": "2021-09-25 02:19:15",
    "GameLength": "23m 24s",
    "kill": "4",
    "Death": "6",
    "Assist": "5",
    "KDARatio": "1.50:1",
    "Badge1": "Double Kill",
    "Badge2": "empty",
    "champion": "Talon",
    "Tier_Average": "Master",
    "Control_Ward": "empty",
    "teammate_champion0": "Renekton",
    "teammate_id0": "your fearness",
    "teammate_champion1": "Lee Sin",
    "teammate_id1": "안개 가 낀 하늘",
    "teammate_champion2": "LeBlanc",
    "teammate_id2": "New ID",
    "teammate_champion3": "Ezreal",
    "teammate_id3": "웅이애옹",
    "teammate_champion4": "Leona",
    "teammate_id4": "2021Worlds0173",
    "enermy_champion0": "Camille",
    "enermy_id0": "TOPKING",
    "enermy_champion1": "Talon",
    "enermy_id1": "Ma1ibu night",
    "enermy_champion2": "Galio",
    "enermy_id2": "리하우",
    "enermy_champion3": "Lucian",
    "enermy_id3": "Axiyo",
    "enermy_champion4": "Rell",
    "enermy_id4": "렐복치"
  },
  "5473736814": {
    "gameID": "5473736814",
    "gameResult": "win",
    "GameType": "Ranked Solo",
    "gameTime_string": "2021-09-25 01:42:50",
    "GameLength": "22m 43s",
    "kill": "8",
    "Death": "3",
    "Assist": "14",
    "KDARatio": "7.33:1",
    "Badge1": "empty",
    "Badge2": "empty",
    "champion": "Zed",
    "Tier_Average": "Master",
    "Control_Ward": "empty",
    "teammate_champion0": "Camille",
    "teammate_id0": "TOPKING",
    "teammate_champion1": "Zed",
    "teammate_id1": "Ma1ibu night",
    "teammate_champion2": "Akali",
    "teammate_id2": "4cm",
    "teammate_champion3": "Aphelios",
    "teammate_id3": "Exusia",
    "teammate_champion4": "Alistar",
    "teammate_id4": "2021Worlds0173",
    "enermy_champion0": "Lee Sin",
    "enermy_id0": "i will pro",
    "enermy_champion1": "Diana",
    "enermy_id1": "AKAJugkiller",
    "enermy_champion2": "Yasuo",
    "enermy_id2": "타락한 숟가락",
    "enermy_champion3": "Kai'Sa",
    "enermy_id3": "텐비 서프 라테일",
    "enermy_champion4": "Taric",
    "enermy_id4": "Pooh n Bene"
  },
  "5473648188": {
    "gameID": "5473648188",
    "gameResult": "win",
    "GameType": "Ranked Solo",
    "gameTime_string": "2021-09-25 01:01:30",
    "GameLength": "16m 9s",
    "kill": "5",
    "Death": "2",
    "Assist": "6",
    "KDARatio": "5.50:1",
    "Badge1": "Double Kill",
    "Badge2": "empty",
    "champion": "Qiyana",
    "Tier_Average": "Diamond 1",
    "Control_Ward": "empty",
    "teammate_champion0": "Ryze",
    "teammate_id0": "mu ze xi",
    "teammate_champion1": "Talon",
    "teammate_id1": "yon gan niu niu",
    "teammate_champion2": "Galio",
    "teammate_id2": "YueGuangZhiXia",
    "teammate_champion3": "Jhin",
    "teammate_id3": "Dalsuy",
    "teammate_champion4": "Thresh",
    "teammate_id4": "Axiyo",
    "enermy_champion0": "Camille",
    "enermy_id0": "TOPKING",
    "enermy_champion1": "Qiyana",
    "enermy_id1": "Ma1ibu night",
    "enermy_champion2": "Nunu & Willump",
    "enermy_id2": "리하우",
    "enermy_champion3": "Ezreal",
    "enermy_id3": "숲장훈",
    "enermy_champion4": "Bard",
    "enermy_id4": "2007 Pykeking"
  },
  "5473547197": {
    "gameID": "5473547197",
    "gameResult": "win",
    "GameType": "Ranked Solo",
    "gameTime_string": "2021-09-25 00:19:15",
    "GameLength": "20m 44s",
    "kill": "8",
    "Death": "2",
    "Assist": "11",
    "KDARatio": "9.50:1",
    "Badge1": "Double Kill",
    "Badge2": "empty",
    "champion": "Taliyah",
    "Tier_Average": "Master",
    "Control_Ward": "empty",
    "teammate_champion0": "Jayce",
    "teammate_id0": "보는 각이 달라",
    "teammate_champion1": "Lee Sin",
    "teammate_id1": "조댁근1",
    "teammate_champion2": "Lulu",
    "teammate_id2": "서창훈",
    "teammate_champion3": "Samira",
    "teammate_id3": "마왕 아들",
    "teammate_champion4": "Nautilus",
    "teammate_id4": "Kratoscc",
    "enermy_champion0": "Graves",
    "enermy_id0": "TOPKING",
    "enermy_champion1": "Taliyah",
    "enermy_id1": "Ma1ibu night",
    "enermy_champion2": "Zed",
    "enermy_id2": "챌 제",
    "enermy_champion3": "Kai'Sa",
    "enermy_id3": "T10 Berserker",
    "enermy_champion4": "Amumu",
    "enermy_id4": "lIlIIllIllllllll"
  },
  "5471851493": {
    "gameID": "5471851493",
    "gameResult": "lose",
    "GameType": "Ranked Solo",
    "gameTime_string": "2021-09-24 04:03:19",
    "GameLength": "30m 1s",
    "kill": "7",
    "Death": "5",
    "Assist": "8",
    "KDARatio": "3.00:1",
    "Badge1": "ACE",
    "Badge2": "empty",
    "champion": "Lillia",
    "Tier_Average": "Diamond 1",
    "Control_Ward": "empty",
    "teammate_champion0": "Vayne",
    "teammate_id0": "Larg2",
    "teammate_champion1": "Graves",
    "teammate_id1": "Dahuangren1",
    "teammate_champion2": "Sylas",
    "teammate_id2": "xwbzgsjsd",
    "teammate_champion3": "Draven",
    "teammate_id3": "졸려죽겠다진짜",
    "teammate_champion4": "Thresh",
    "teammate_id4": "Eslnd",
    "enermy_champion0": "Qiyana",
    "enermy_id0": "이가은",
    "enermy_champion1": "Lillia",
    "enermy_id1": "Ma1ibu night",
    "enermy_champion2": "Lucian",
    "enermy_id2": "TOPKING",
    "enermy_champion3": "Aphelios",
    "enermy_id3": "waste time",
    "enermy_champion4": "Lulu",
    "enermy_id4": "서울고속도로"
  },
  "5471800120": {
    "gameID": "5471800120",
    "gameResult": "win",
    "GameType": "Ranked Solo",
    "gameTime_string": "2021-09-24 03:17:37",
    "GameLength": "22m 34s",
    "kill": "16",
    "Death": "0",
    "Assist": "9",
    "KDARatio": "Perfect",
    "Badge1": "Double Kill",
    "Badge2": "MVP",
    "champion": "Nidalee",
    "Tier_Average": "Diamond 1",
    "Control_Ward": "empty",
    "teammate_champion0": "Jayce",
    "teammate_id0": "TOPKING",
    "teammate_champion1": "Nidalee",
    "teammate_id1": "Ma1ibu night",
    "teammate_champion2": "Pantheon",
    "teammate_id2": "기 찬",
    "teammate_champion3": "Samira",
    "teammate_id3": "ad Noob sorry",
    "teammate_champion4": "Alistar",
    "teammate_id4": "주말엔동희와산책",
    "enermy_champion0": "Tryndamere",
    "enermy_id0": "생각하는사람1",
    "enermy_champion1": "Kayn",
    "enermy_id1": "믜 진",
    "enermy_champion2": "Zed",
    "enermy_id2": "mu ze xi",
    "enermy_champion3": "Draven",
    "enermy_id3": "yelb",
    "enermy_champion4": "Amumu",
    "enermy_id4": " chacka chicky"
  },
  "5471717750": {
    "gameID": "5471717750",
    "gameResult": "win",
    "GameType": "Ranked Solo",
    "gameTime_string": "2021-09-24 02:41:44",
    "GameLength": "20m 25s",
    "kill": "10",
    "Death": "3",
    "Assist": "6",
    "KDARatio": "5.33:1",
    "Badge1": "Double Kill",
    "Badge2": "empty",
    "champion": "Zed",
    "Tier_Average": "Diamond 1",
    "Control_Ward": "empty",
    "teammate_champion0": "Heimerdinger",
    "teammate_id0": "현욱 정",
    "teammate_champion1": "Zed",
    "teammate_id1": "Ma1ibu night",
    "teammate_champion2": "Sylas",
    "teammate_id2": "TOPKING",
    "teammate_champion3": "Twitch",
    "teammate_id3": "little hamburger",
    "teammate_champion4": "Lulu",
    "teammate_id4": "Humble good",
    "enermy_champion0": "Akali",
    "enermy_id0": "좋은 것만 남아",
    "enermy_champion1": "Talon",
    "enermy_id1": "Top chord one",
    "enermy_champion2": "Jarvan IV",
    "enermy_id2": "낮에뜨는 달과 별",
    "enermy_champion3": "Draven",
    "enermy_id3": "yelb",
    "enermy_champion4": "Amumu",
    "enermy_id4": " chacka chicky"
  },
  "5471752833": {
    "gameID": "5471752833",
    "gameResult": "lose",
    "GameType": "Ranked Solo",
    "gameTime_string": "2021-09-24 01:59:01",
    "GameLength": "27m 37s",
    "kill": "8",
    "Death": "7",
    "Assist": "3",
    "KDARatio": "1.57:1",
    "Badge1": "Double Kill",
    "Badge2": "ACE",
    "champion": "Viego",
    "Tier_Average": "Diamond 1",
    "Control_Ward": "empty",
    "teammate_champion0": "Kennen",
    "teammate_id0": "해일해2해삼",
    "teammate_champion1": "Lee Sin",
    "teammate_id1": "The Battle Cats",
    "teammate_champion2": "Qiyana",
    "teammate_id2": "선혈포식자안가요",
    "teammate_champion3": "Miss Fortune",
    "teammate_id3": "Kog Maw hello",
    "teammate_champion4": "Karma",
    "teammate_id4": "따뜻하게대해줘요",
    "enermy_champion0": "Sejuani",
    "enermy_id0": "TOPKING",
    "enermy_champion1": "Viego",
    "enermy_id1": "Ma1ibu night",
    "enermy_champion2": "LeBlanc",
    "enermy_id2": "Dreaming Future",
    "enermy_champion3": "Ezreal",
    "enermy_id3": "꽃바다인질",
    "enermy_champion4": "Braum",
    "enermy_id4": "xiaoxinchaoren"
  },
  "5469804461": {
    "gameID": "5469804461",
    "gameResult": "win",
    "GameType": "Ranked Solo",
    "gameTime_string": "2021-09-23 02:52:31",
    "GameLength": "25m 41s",
    "kill": "8",
    "Death": "3",
    "Assist": "7",
    "KDARatio": "5.00:1",
    "Badge1": "Double Kill",
    "Badge2": "MVP",
    "champion": "Zed",
    "Tier_Average": "Diamond 1",
    "Control_Ward": "empty",
    "teammate_champion0": "Malphite",
    "teammate_id0": "TOPKING",
    "teammate_champion1": "Zed",
    "teammate_id1": "Ma1ibu night",
    "teammate_champion2": "LeBlanc",
    "teammate_id2": "하얗고예쁨",
    "teammate_champion3": "Caitlyn",
    "teammate_id3": "짐승 잡초 인간",
    "teammate_champion4": "Lux",
    "teammate_id4": "szpt",
    "enermy_champion0": "Fiora",
    "enermy_id0": "애기공룡 주상",
    "enermy_champion1": "Jarvan IV",
    "enermy_id1": "Dahuangren1",
    "enermy_champion2": "Karma",
    "enermy_id2": "ninichu",
    "enermy_champion3": "Lucian",
    "enermy_id3": "BerylSKS",
    "enermy_champion4": "Nami",
    "enermy_id4": "FNmhoMmaITl8Z50I"
  },
  "5469759598": {
    "gameID": "5469759598",
    "gameResult": "win",
    "GameType": "Ranked Solo",
    "gameTime_string": "2021-09-23 02:08:33",
    "GameLength": "31m 57s",
    "kill": "6",
    "Death": "7",
    "Assist": "12",
    "KDARatio": "2.57:1",
    "Badge1": "Double Kill",
    "Badge2": "empty",
    "champion": "Lillia",
    "Tier_Average": "Diamond 2",
    "Control_Ward": "empty",
    "teammate_champion0": "Lucian",
    "teammate_id0": "TOPKING",
    "teammate_champion1": "Lillia",
    "teammate_id1": "Ma1ibu night",
    "teammate_champion2": "Talon",
    "teammate_id2": "화원 아기",
    "teammate_champion3": "Miss Fortune",
    "teammate_id3": "xixixlxix",
    "teammate_champion4": "Seraphine",
    "teammate_id4": "DWG BeryL",
    "enermy_champion0": "Gangplank",
    "enermy_id0": "파 고",
    "enermy_champion1": "Taliyah",
    "enermy_id1": "로이갓전용노예",
    "enermy_champion2": "Sylas",
    "enermy_id2": "youtube 비브이",
    "enermy_champion3": "Aphelios",
    "enermy_id3": "BerylSKS",
    "enermy_champion4": "Thresh",
    "enermy_id4": "FNmhoMmaITl8Z50I"
  },
  "5452792931": {
    "gameID": "5452792931",
    "gameResult": "win",
    "GameType": "Ranked Solo",
    "gameTime_string": "2021-09-15 00:12:07",
    "GameLength": "30m 5s",
    "kill": "19",
    "Death": "5",
    "Assist": "7",
    "KDARatio": "5.20:1",
    "Badge1": "empty",
    "Badge2": "empty",
    "champion": "Zed",
    "Tier_Average": "Diamond 1",
    "Control_Ward": "empty",
    "teammate_champion0": "Kennen",
    "teammate_id0": "내점수에잠이오냐",
    "teammate_champion1": "Talon",
    "teammate_id1": "HLE qkralfm",
    "teammate_champion2": "Zoe",
    "teammate_id2": "송의진제자장민수",
    "teammate_champion3": "Varus",
    "teammate_id3": "산중호걸 호랑",
    "teammate_champion4": "Blitzcrank",
    "teammate_id4": "sorrysrysupgap",
    "enermy_champion0": "Vladimir",
    "enermy_id0": "모두모두항복하길",
    "enermy_champion1": "Zed",
    "enermy_id1": "Ma1ibu night",
    "enermy_champion2": "Taliyah",
    "enermy_id2": "AF BuLLDoG",
    "enermy_champion3": "Jinx",
    "enermy_id3": "dlrlrhtlvek1",
    "enermy_champion4": "Thresh",
    "enermy_id4": "점수나락감"
  },
  "5445254368": {
    "gameID": "5445254368",
    "gameResult": "win",
    "GameType": "Ranked Solo",
    "gameTime_string": "2021-09-11 04:04:51",
    "GameLength": "15m 37s",
    "kill": "5",
    "Death": "1",
    "Assist": "5",
    "KDARatio": "10.00:1",
    "Badge1": "Double Kill",
    "Badge2": "MVP",
    "champion": "Olaf",
    "Tier_Average": "Platinum 1",
    "Control_Ward": "empty",
    "teammate_champion0": "Irelia",
    "teammate_id0": "왕원희",
    "teammate_champion1": "Ekko",
    "teammate_id1": "Zhonguo Zhu",
    "teammate_champion2": "Zed",
    "teammate_id2": "라2엇밸패팀앰갈",
    "teammate_champion3": "Aphelios",
    "teammate_id3": "AFTV 원장",
    "teammate_champion4": "Blitzcrank",
    "teammate_id4": "Lab C",
    "enermy_champion0": "Fiora",
    "enermy_id0": "모두모두항복하길",
    "enermy_champion1": "Olaf",
    "enermy_id1": "Ma1ibu night",
    "enermy_champion2": "Galio",
    "enermy_id2": "1xn fans",
    "enermy_champion3": "Samira",
    "enermy_id3": "Ljx002",
    "enermy_champion4": "Sett",
    "enermy_id4": "Wzy002"
  },
  "5272779053": {
    "gameID": "5272779053",
    "gameResult": "win",
    "GameType": "Nexus Blitz",
    "gameTime_string": "2021-06-20 00:34:32",
    "GameLength": "17m 9s",
    "kill": "17",
    "Death": "5",
    "Assist": "13",
    "KDARatio": "6.00:1",
    "Badge1": "Quadra Kill",
    "Badge2": "empty",
    "champion": "Viego",
    "Tier_Average": "empty",
    "Control_Ward": "empty",
    "teammate_champion0": "Lucian",
    "teammate_id0": "Mou",
    "teammate_champion1": "Jarvan IV",
    "teammate_id1": "Lapierre",
    "teammate_champion2": "Viktor",
    "teammate_id2": "골없후왕",
    "teammate_champion3": "Kog'Maw",
    "teammate_id3": "tip tap toc",
    "teammate_champion4": "Master Yi",
    "teammate_id4": "NeroClaudius7",
    "enermy_champion0": "Varus",
    "enermy_id0": "진돛개",
    "enermy_champion1": "Viego",
    "enermy_id1": "Ma1ibu night",
    "enermy_champion2": "Malphite",
    "enermy_id2": "감정의요인",
    "enermy_champion3": "Pyke",
    "enermy_id3": "에스파컴백기원",
    "enermy_champion4": "Sett",
    "enermy_id4": "깨비드릴조7777"
  },
  "5235934512": {
    "gameID": "5235934512",
    "gameResult": "lose",
    "GameType": "Ranked Solo",
    "gameTime_string": "2021-06-02 01:22:58",
    "GameLength": "19m 34s",
    "kill": "1",
    "Death": "6",
    "Assist": "4",
    "KDARatio": "0.83:1",
    "Badge1": "ACE",
    "Badge2": "empty",
    "champion": "Diana",
    "Tier_Average": "Master",
    "Control_Ward": "empty",
    "teammate_champion0": "Sylas",
    "teammate_id0": "나는성공할것이다",
    "teammate_champion1": "Kindred",
    "teammate_id1": "멍청작은서",
    "teammate_champion2": "Zoe",
    "teammate_id2": "배달음식요기요",
    "teammate_champion3": "Miss Fortune",
    "teammate_id3": "frqi",
    "teammate_champion4": "Thresh",
    "teammate_id4": "Xiaohaichuishi",
    "enermy_champion0": "Gangplank",
    "enermy_id0": "아재얼귤",
    "enermy_champion1": "Diana",
    "enermy_id1": "Ma1ibu night",
    "enermy_champion2": "Rumble",
    "enermy_id2": "haoyunsenming",
    "enermy_champion3": "Yasuo",
    "enermy_id3": "WMNMMN",
    "enermy_champion4": "Alistar",
    "enermy_id4": "진짜 어려워"
  },
  "5221913012": {
    "gameID": "5221913012",
    "gameResult": "lose",
    "GameType": "Ranked Solo",
    "gameTime_string": "2021-05-26 16:05:59",
    "GameLength": "15m 20s",
    "kill": "2",
    "Death": "6",
    "Assist": "0",
    "KDARatio": "0.33:1",
    "Badge1": "empty",
    "Badge2": "empty",
    "champion": "Jayce",
    "Tier_Average": "Master",
    "Control_Ward": "empty",
    "teammate_champion0": "Wukong",
    "teammate_id0": "Water monkey",
    "teammate_champion1": "Rumble",
    "teammate_id1": "2660745977530048",
    "teammate_champion2": "Sylas",
    "teammate_id2": "im fine thx you",
    "teammate_champion3": "Sett",
    "teammate_id3": "talking shlt",
    "teammate_champion4": "Senna",
    "teammate_id4": "09 AD klng",
    "enermy_champion0": "Tryndamere",
    "enermy_id0": "AminaAmina",
    "enermy_champion1": "Rengar",
    "enermy_id1": "aozhizhuiliezhe",
    "enermy_champion2": "Jayce",
    "enermy_id2": "Ma1ibu night",
    "enermy_champion3": "Tristana",
    "enermy_id3": "kelinn",
    "enermy_champion4": "Lulu",
    "enermy_id4": "yang zhi bu ou"
  },
  "5221856783": {
    "gameID": "5221856783",
    "gameResult": "lose",
    "GameType": "Ranked Solo",
    "gameTime_string": "2021-05-26 15:30:25",
    "GameLength": "34m 2s",
    "kill": "9",
    "Death": "6",
    "Assist": "15",
    "KDARatio": "4.00:1",
    "Badge1": "Double Kill",
    "Badge2": "ACE",
    "champion": "Lee Sin",
    "Tier_Average": "Master",
    "Control_Ward": "empty",
    "teammate_champion0": "Sylas",
    "teammate_id0": "p9815",
    "teammate_champion1": "Lee Sin",
    "teammate_id1": "Ma1ibu night",
    "teammate_champion2": "Sett",
    "teammate_id2": "혜지명1",
    "teammate_champion3": "Tahm Kench",
    "teammate_id3": "하루에 18판",
    "teammate_champion4": "Senna",
    "teammate_id4": "프레이신부서연이",
    "enermy_champion0": "Draven",
    "enermy_id0": "드레이븐원챔6",
    "enermy_champion1": "Nautilus",
    "enermy_id1": "lIlIIIIlllIIlII",
    "enermy_champion2": "Akali",
    "enermy_id2": "Fox B Mg",
    "enermy_champion3": "Ezreal",
    "enermy_id3": "FLAGGED 22593849",
    "enermy_champion4": "Bard",
    "enermy_id4": "Mocha"
  },
  "5221843200": {
    "gameID": "5221843200",
    "gameResult": "win",
    "GameType": "Ranked Solo",
    "gameTime_string": "2021-05-26 14:44:52",
    "GameLength": "25m 2s",
    "kill": "10",
    "Death": "2",
    "Assist": "9",
    "KDARatio": "9.50:1",
    "Badge1": "MVP",
    "Badge2": "empty",
    "champion": "Hecarim",
    "Tier_Average": "Master",
    "Control_Ward": "empty",
    "teammate_champion0": "Gangplank",
    "teammate_id0": "xiao ke tang",
    "teammate_champion1": "Hecarim",
    "teammate_id1": "Ma1ibu night",
    "teammate_champion2": "Sylas",
    "teammate_id2": "p9815",
    "teammate_champion3": "Varus",
    "teammate_id3": "납득이 안가요1",
    "teammate_champion4": "Karma",
    "teammate_id4": "Mocha",
    "enermy_champion0": "Jayce",
    "enermy_id0": "북극곰 아프다",
    "enermy_champion1": "Udyr",
    "enermy_id1": "yang zhi bu ou",
    "enermy_champion2": "Master Yi",
    "enermy_id2": "im fine thx you",
    "enermy_champion3": "Kog'Maw",
    "enermy_id3": "LSB Prince",
    "enermy_champion4": "Lulu",
    "enermy_id4": "하루에 18판"
  },
  "5221709928": {
    "gameID": "5221709928",
    "gameResult": "win",
    "GameType": "Ranked Solo",
    "gameTime_string": "2021-05-26 14:00:21",
    "GameLength": "17m 1s",
    "kill": "5",
    "Death": "3",
    "Assist": "6",
    "KDARatio": "3.67:1",
    "Badge1": "empty",
    "Badge2": "empty",
    "champion": "Diana",
    "Tier_Average": "Master",
    "Control_Ward": "empty",
    "teammate_champion0": "Fiora",
    "teammate_id0": "long yan jing xi",
    "teammate_champion1": "Diana",
    "teammate_id1": "Ma1ibu night",
    "teammate_champion2": "Yone",
    "teammate_id2": "Denity",
    "teammate_champion3": "Jinx",
    "teammate_id3": "맵을 보다",
    "teammate_champion4": "Lulu",
    "teammate_id4": "댕실댕실이",
    "enermy_champion0": "Sejuani",
    "enermy_id0": "TW Choco",
    "enermy_champion1": "Hecarim",
    "enermy_id1": "옹 괏",
    "enermy_champion2": "Sett",
    "enermy_id2": "최후의 돌파구",
    "enermy_champion3": "Kai'Sa",
    "enermy_id3": "yyyyyzyyy",
    "enermy_champion4": "Karma",
    "enermy_id4": "Palette6"
  },
  "5221767477": {
    "gameID": "5221767477",
    "gameResult": "win",
    "GameType": "Ranked Solo",
    "gameTime_string": "2021-05-26 13:25:26",
    "GameLength": "11m 7s",
    "kill": "4",
    "Death": "2",
    "Assist": "5",
    "KDARatio": "4.50:1",
    "Badge1": "Double Kill",
    "Badge2": "empty",
    "champion": "Elise",
    "Tier_Average": "Master",
    "Control_Ward": "empty",
    "teammate_champion0": "Renekton",
    "teammate_id0": "ZEST1",
    "teammate_champion1": "Elise",
    "teammate_id1": "Ma1ibu night",
    "teammate_champion2": "Vladimir",
    "teammate_id2": "치사량99퍼",
    "teammate_champion3": "Jhin",
    "teammate_id3": "yyyyyzyyy",
    "teammate_champion4": "Galio",
    "teammate_id4": "나는알면서당해줘",
    "enermy_champion0": "Sylas",
    "enermy_id0": "탈론쓰레기챔프",
    "enermy_champion1": "Lee Sin",
    "enermy_id1": "배고파서 슬퍼",
    "enermy_champion2": "Alistar",
    "enermy_id2": "삼각러",
    "enermy_champion3": "Kai'Sa",
    "enermy_id3": "희망넘치는닉네임",
    "enermy_champion4": "Singed",
    "enermy_id4": "6월 호랑이"
  },
  "5209128788": {
    "gameID": "5209128788",
    "gameResult": "win",
    "GameType": "Ranked Solo",
    "gameTime_string": "2021-05-20 16:34:30",
    "GameLength": "21m 57s",
    "kill": "11",
    "Death": "2",
    "Assist": "4",
    "KDARatio": "7.50:1",
    "Badge1": "Double Kill",
    "Badge2": "MVP",
    "champion": "Kindred",
    "Tier_Average": "Master",
    "Control_Ward": "empty",
    "teammate_champion0": "Gwen",
    "teammate_id0": "처음부터다시하다",
    "teammate_champion1": "Kindred",
    "teammate_id1": "Ma1ibu night",
    "teammate_champion2": "Sylas",
    "teammate_id2": "Make Me M0ve",
    "teammate_champion3": "Samira",
    "teammate_id3": "hggbexrloo",
    "teammate_champion4": "Nautilus",
    "teammate_id4": "프랩1",
    "enermy_champion0": "Cassiopeia",
    "enermy_id0": "킬러톱",
    "enermy_champion1": "Lee Sin",
    "enermy_id1": "asfgasgagasf",
    "enermy_champion2": "Twisted Fate",
    "enermy_id2": "전 모르겠어요",
    "enermy_champion3": "Ezreal",
    "enermy_id3": "아름답게 보여요",
    "enermy_champion4": "Bard",
    "enermy_id4": "2562485188273664"
  },
  "5209053947": {
    "gameID": "5209053947",
    "gameResult": "lose",
    "GameType": "Ranked Solo",
    "gameTime_string": "2021-05-20 15:53:23",
    "GameLength": "26m 11s",
    "kill": "5",
    "Death": "8",
    "Assist": "5",
    "KDARatio": "1.25:1",
    "Badge1": "Double Kill",
    "Badge2": "empty",
    "champion": "Rumble",
    "Tier_Average": "Master",
    "Control_Ward": "empty",
    "teammate_champion0": "Fiora",
    "teammate_id0": "1111110",
    "teammate_champion1": "Rumble",
    "teammate_id1": "Ma1ibu night",
    "teammate_champion2": "Zed",
    "teammate_id2": "2680630405572576",
    "teammate_champion3": "Lucian",
    "teammate_id3": "dkkkkkkkkkkkk",
    "teammate_champion4": "Galio",
    "teammate_id4": "xiaoxiaozhizhu",
    "enermy_champion0": "Sett",
    "enermy_id0": "페리글라스 블루",
    "enermy_champion1": "Nidalee",
    "enermy_id1": "asfgasgagasf",
    "enermy_champion2": "Darius",
    "enermy_id2": "bwdchzb",
    "enermy_champion3": "Ezreal",
    "enermy_id3": "2598491461805184",
    "enermy_champion4": "Bard",
    "enermy_id4": "2562485188273664"
  },
  "5209080040": {
    "gameID": "5209080040",
    "gameResult": "lose",
    "GameType": "Ranked Solo",
    "gameTime_string": "2021-05-20 15:19:31",
    "GameLength": "27m 30s",
    "kill": "8",
    "Death": "8",
    "Assist": "10",
    "KDARatio": "2.25:1",
    "Badge1": "ACE",
    "Badge2": "empty",
    "champion": "Kindred",
    "Tier_Average": "Master",
    "Control_Ward": "empty",
    "teammate_champion0": "Lucian",
    "teammate_id0": "2598491461805184",
    "teammate_champion1": "Kindred",
    "teammate_id1": "Ma1ibu night",
    "teammate_champion2": "Jax",
    "teammate_id2": "아자 아자 아자",
    "teammate_champion3": "Jinx",
    "teammate_id3": "fdadffdfa",
    "teammate_champion4": "Blitzcrank",
    "teammate_id4": "skxj",
    "enermy_champion0": "Aatrox",
    "enermy_id0": "fashion여쟈",
    "enermy_champion1": "Elise",
    "enermy_id1": "03zero",
    "enermy_champion2": "Zed",
    "enermy_id2": "2680630405572576",
    "enermy_champion3": "Karthus",
    "enermy_id3": "asfgasgagasf",
    "enermy_champion4": "Nami",
    "enermy_id4": "2562485188273664"
  },
  "5208967213": {
    "gameID": "5208967213",
    "gameResult": "win",
    "GameType": "Ranked Solo",
    "gameTime_string": "2021-05-20 14:42:46",
    "GameLength": "21m 8s",
    "kill": "8",
    "Death": "5",
    "Assist": "10",
    "KDARatio": "3.60:1",
    "Badge1": "Double Kill",
    "Badge2": "MVP",
    "champion": "Lee Sin",
    "Tier_Average": "Master",
    "Control_Ward": "empty",
    "teammate_champion0": "Cassiopeia",
    "teammate_id0": "킬러톱",
    "teammate_champion1": "Rek'Sai",
    "teammate_id1": "dkkkkkkkkkkkk",
    "teammate_champion2": "Twisted Fate",
    "teammate_id2": "전 모르겠어요",
    "teammate_champion3": "Kai'Sa",
    "teammate_id3": "BSM 문효준",
    "teammate_champion4": "Sett",
    "teammate_id4": "wyhzl",
    "enermy_champion0": "Akali",
    "enermy_id0": "hua di wei lao",
    "enermy_champion1": "Lee Sin",
    "enermy_id1": "Ma1ibu night",
    "enermy_champion2": "Sylas",
    "enermy_id2": "전설이 될 남자",
    "enermy_champion3": "Jinx",
    "enermy_id3": "Tlcc 1 Camille",
    "enermy_champion4": "Thresh",
    "enermy_id4": "Mocha"
  },
  "5209003248": {
    "gameID": "5209003248",
    "gameResult": "win",
    "GameType": "Ranked Solo",
    "gameTime_string": "2021-05-20 14:06:41",
    "GameLength": "25m 52s",
    "kill": "5",
    "Death": "5",
    "Assist": "12",
    "KDARatio": "3.40:1",
    "Badge1": "empty",
    "Badge2": "empty",
    "champion": "Nocturne",
    "Tier_Average": "Master",
    "Control_Ward": "empty",
    "teammate_champion0": "Sett",
    "teammate_id0": "zxczxcasdaxd",
    "teammate_champion1": "Udyr",
    "teammate_id1": "depressingx",
    "teammate_champion2": "Viktor",
    "teammate_id2": "87Kepler",
    "teammate_champion3": "Tristana",
    "teammate_id3": "DRX Bory",
    "teammate_champion4": "Leona",
    "teammate_id4": "muooii",
    "enermy_champion0": "Aatrox",
    "enermy_id0": "페리글라스 블루",
    "enermy_champion1": "Nocturne",
    "enermy_id1": "Ma1ibu night",
    "enermy_champion2": "Sylas",
    "enermy_id2": "누가 널 봤어",
    "enermy_champion3": "Kai'Sa",
    "enermy_id3": "wqnflqwnfoqw",
    "enermy_champion4": "Alistar",
    "enermy_id4": "363363363"
  },
  "5209030162": {
    "gameID": "5209030162",
    "gameResult": "win",
    "GameType": "Ranked Solo",
    "gameTime_string": "2021-05-20 13:31:08",
    "GameLength": "23m 40s",
    "kill": "3",
    "Death": "1",
    "Assist": "8",
    "KDARatio": "11.00:1",
    "Badge1": "empty",
    "Badge2": "empty",
    "champion": "Lee Sin",
    "Tier_Average": "Master",
    "Control_Ward": "empty",
    "teammate_champion0": "Sylas",
    "teammate_id0": "파천신권",
    "teammate_champion1": "Viego",
    "teammate_id1": "흐에에에엥",
    "teammate_champion2": "LeBlanc",
    "teammate_id2": "멍멍이5",
    "teammate_champion3": "Aphelios",
    "teammate_id3": "bxz12czxbz",
    "teammate_champion4": "Thresh",
    "teammate_id4": "363363363",
    "enermy_champion0": "Wukong",
    "enermy_id0": "Water monkey",
    "enermy_champion1": "Lee Sin",
    "enermy_id1": "Ma1ibu night",
    "enermy_champion2": "Galio",
    "enermy_id2": "Fox B Mg",
    "enermy_champion3": "Samira",
    "enermy_id3": "2714623374157568",
    "enermy_champion4": "Alistar",
    "enermy_id4": "댕실댕실이"
  },
  "5204915428": {
    "gameID": "5204915428",
    "gameResult": "lose",
    "GameType": "Ranked Solo",
    "gameTime_string": "2021-05-18 21:47:13",
    "GameLength": "20m 53s",
    "kill": "10",
    "Death": "6",
    "Assist": "3",
    "KDARatio": "2.17:1",
    "Badge1": "Double Kill",
    "Badge2": "ACE",
    "champion": "Gragas",
    "Tier_Average": "Master",
    "Control_Ward": "empty",
    "teammate_champion0": "Wukong",
    "teammate_id0": "4초스크류",
    "teammate_champion1": "Lee Sin",
    "teammate_id1": "넥서스 남아있다",
    "teammate_champion2": "LeBlanc",
    "teammate_id2": "HLE Mask",
    "teammate_champion3": "Lucian",
    "teammate_id3": "Shadow Ming9",
    "teammate_champion4": "Taliyah",
    "teammate_id4": "N냐옹N",
    "enermy_champion0": "Sett",
    "enermy_id0": "haohaohao3",
    "enermy_champion1": "Gragas",
    "enermy_id1": "Ma1ibu night",
    "enermy_champion2": "Jayce",
    "enermy_id2": "UMBBBBBBBBB",
    "enermy_champion3": "Ezreal",
    "enermy_id3": "소환사의진",
    "enermy_champion4": "Bard",
    "enermy_id4": "2562474652387200"
  },
  "5204779575": {
    "gameID": "5204779575",
    "gameResult": "win",
    "GameType": "Ranked Solo",
    "gameTime_string": "2021-05-18 21:18:11",
    "GameLength": "22m 0s",
    "kill": "16",
    "Death": "1",
    "Assist": "12",
    "KDARatio": "28.00:1",
    "Badge1": "Triple Kill",
    "Badge2": "MVP",
    "champion": "Kindred",
    "Tier_Average": "Master",
    "Control_Ward": "empty",
    "teammate_champion0": "Maokai",
    "teammate_id0": "팔공산 야생곰",
    "teammate_champion1": "Kindred",
    "teammate_id1": "Ma1ibu night",
    "teammate_champion2": "Galio",
    "teammate_id2": "marifanaemon",
    "teammate_champion3": "Kai'Sa",
    "teammate_id3": "희망넘치는닉네임",
    "teammate_champion4": "Nautilus",
    "teammate_id4": "카카오배그",
    "enermy_champion0": "Aatrox",
    "enermy_id0": "소환사의진",
    "enermy_champion1": "Lee Sin",
    "enermy_id1": "SushiZz",
    "enermy_champion2": "Sylas",
    "enermy_id2": "Denity",
    "enermy_champion3": "Tristana",
    "enermy_id3": "iuself",
    "enermy_champion4": "Blitzcrank",
    "enermy_id4": "홍상현 암살부대"
  },
  "5204832006": {
    "gameID": "5204832006",
    "gameResult": "lose",
    "GameType": "Ranked Solo",
    "gameTime_string": "2021-05-18 20:45:08",
    "GameLength": "27m 36s",
    "kill": "5",
    "Death": "6",
    "Assist": "3",
    "KDARatio": "1.33:1",
    "Badge1": "empty",
    "Badge2": "empty",
    "champion": "Jayce",
    "Tier_Average": "Master",
    "Control_Ward": "empty",
    "teammate_champion0": "Renekton",
    "teammate_id0": "forget i",
    "teammate_champion1": "Lee Sin",
    "teammate_id1": "asfgasgagasf",
    "teammate_champion2": "Zoe",
    "teammate_id2": "진쏘킴",
    "teammate_champion3": "Tristana",
    "teammate_id3": "GUCCI G4NG",
    "teammate_champion4": "Bard",
    "teammate_id4": "2562485188273664",
    "enermy_champion0": "Shen",
    "enermy_id0": "모두모두항복하걸",
    "enermy_champion1": "Taliyah",
    "enermy_id1": "넥서스 남아있다",
    "enermy_champion2": "Jayce",
    "enermy_id2": "Ma1ibu night",
    "enermy_champion3": "Kai'Sa",
    "enermy_id3": "오스기",
    "enermy_champion4": "Leona",
    "enermy_id4": "Danrenguiiiiiii"
  },
  "5204696142": {
    "gameID": "5204696142",
    "gameResult": "lose",
    "GameType": "Ranked Solo",
    "gameTime_string": "2021-05-18 20:06:28",
    "GameLength": "29m 26s",
    "kill": "10",
    "Death": "9",
    "Assist": "11",
    "KDARatio": "2.33:1",
    "Badge1": "Double Kill",
    "Badge2": "ACE",
    "champion": "Nocturne",
    "Tier_Average": "Master",
    "Control_Ward": "empty",
    "teammate_champion0": "Gwen",
    "teammate_id0": "배고파더워졸려",
    "teammate_champion1": "Nocturne",
    "teammate_id1": "Ma1ibu night",
    "teammate_champion2": "Zoe",
    "teammate_id2": "단군의청춘부재I",
    "teammate_champion3": "Kai'Sa",
    "teammate_id3": "Cuiller",
    "teammate_champion4": "Nautilus",
    "teammate_id4": "노 빅",
    "enermy_champion0": "Aatrox",
    "enermy_id0": "gonna be my love",
    "enermy_champion1": "Elise",
    "enermy_id1": "퀸태진",
    "enermy_champion2": "Qiyana",
    "enermy_id2": "2672161554687168",
    "enermy_champion3": "Xayah",
    "enermy_id3": "meiyouyuzhao",
    "enermy_champion4": "Karma",
    "enermy_id4": "PING25LIHAI"
  },
  "5203615227": {
    "gameID": "5203615227",
    "gameResult": "win",
    "GameType": "Ranked Solo",
    "gameTime_string": "2021-05-18 01:56:50",
    "GameLength": "20m 0s",
    "kill": "5",
    "Death": "3",
    "Assist": "5",
    "KDARatio": "3.33:1",
    "Badge1": "MVP",
    "Badge2": "empty",
    "champion": "Rumble",
    "Tier_Average": "Master",
    "Control_Ward": "empty",
    "teammate_champion0": "Sett",
    "teammate_id0": "Bluff da shi",
    "teammate_champion1": "Morgana",
    "teammate_id1": "xianxiaosh200",
    "teammate_champion2": "Qiyana",
    "teammate_id2": "Make Me M0ve",
    "teammate_champion3": "Varus",
    "teammate_id3": "록 쏠",
    "teammate_champion4": "Karma",
    "teammate_id4": "ISFP그자체",
    "enermy_champion0": "Irelia",
    "enermy_id0": "haohaohao3",
    "enermy_champion1": "Rumble",
    "enermy_id1": "Ma1ibu night",
    "enermy_champion2": "Sylas",
    "enermy_id2": "cyxiaokeai",
    "enermy_champion3": "Jayce",
    "enermy_id3": "Rascal",
    "enermy_champion4": "Senna",
    "enermy_id4": "살인몬"
  },
  "5203581273": {
    "gameID": "5203581273",
    "gameResult": "win",
    "GameType": "Ranked Solo",
    "gameTime_string": "2021-05-18 01:30:23",
    "GameLength": "29m 9s",
    "kill": "11",
    "Death": "4",
    "Assist": "18",
    "KDARatio": "7.25:1",
    "Badge1": "Double Kill",
    "Badge2": "MVP",
    "champion": "Udyr",
    "Tier_Average": "Master",
    "Control_Ward": "empty",
    "teammate_champion0": "Lee Sin",
    "teammate_id0": "Rascal",
    "teammate_champion1": "Udyr",
    "teammate_id1": "Ma1ibu night",
    "teammate_champion2": "Sylas",
    "teammate_id2": "hewon",
    "teammate_champion3": "Ashe",
    "teammate_id3": "구너상",
    "teammate_champion4": "Gragas",
    "teammate_id4": "편하게 하다",
    "enermy_champion0": "Garen",
    "enermy_id0": "GarenK1ng",
    "enermy_champion1": "Taliyah",
    "enermy_id1": "DOJERI",
    "enermy_champion2": "Jayce",
    "enermy_id2": "담배냄새싫어요",
    "enermy_champion3": "Samira",
    "enermy_id3": "록 쏠",
    "enermy_champion4": "Pyke",
    "enermy_id4": "pyke k1ng"
  },
  "5203466854": {
    "gameID": "5203466854",
    "gameResult": "win",
    "GameType": "Ranked Solo",
    "gameTime_string": "2021-05-18 00:50:06",
    "GameLength": "18m 7s",
    "kill": "3",
    "Death": "3",
    "Assist": "12",
    "KDARatio": "5.00:1",
    "Badge1": "empty",
    "Badge2": "empty",
    "champion": "Kindred",
    "Tier_Average": "Master",
    "Control_Ward": "empty",
    "teammate_champion0": "Lee Sin",
    "teammate_id0": "Rascal",
    "teammate_champion1": "Kindred",
    "teammate_id1": "Ma1ibu night",
    "teammate_champion2": "Akali",
    "teammate_id2": "잘못했어",
    "teammate_champion3": "Twitch",
    "teammate_id3": "룰루 서운한",
    "teammate_champion4": "Nautilus",
    "teammate_id4": "알 쫑",
    "enermy_champion0": "Sett",
    "enermy_id0": "Hippie Dog",
    "enermy_champion1": "Kha'Zix",
    "enermy_id1": "잠 컨",
    "enermy_champion2": "Galio",
    "enermy_id2": "서정언",
    "enermy_champion3": "Kai'Sa",
    "enermy_id3": "버그가났어요",
    "enermy_champion4": "Maokai",
    "enermy_id4": "무위도식의 삶"
  },
  "5203460757": {
    "gameID": "5203460757",
    "gameResult": "win",
    "GameType": "Ranked Solo",
    "gameTime_string": "2021-05-18 00:18:01",
    "GameLength": "23m 25s",
    "kill": "15",
    "Death": "3",
    "Assist": "11",
    "KDARatio": "8.67:1",
    "Badge1": "Double Kill",
    "Badge2": "MVP",
    "champion": "Elise",
    "Tier_Average": "Master",
    "Control_Ward": "empty",
    "teammate_champion0": "Lee Sin",
    "teammate_id0": "Rascal",
    "teammate_champion1": "Elise",
    "teammate_id1": "Ma1ibu night",
    "teammate_champion2": "Nocturne",
    "teammate_id2": "강지원 예비신랑",
    "teammate_champion3": "Samira",
    "teammate_id3": "다람쥐의 총",
    "teammate_champion4": "Galio",
    "teammate_id4": "갈리오 노틸러스",
    "enermy_champion0": "Gangplank",
    "enermy_id0": "아재얼귤",
    "enermy_champion1": "Rumble",
    "enermy_id1": "haoyunsenming",
    "enermy_champion2": "Qiyana",
    "enermy_id2": "2684094399677824",
    "enermy_champion3": "Ezreal",
    "enermy_id3": "다음생엔돌맹이로",
    "enermy_champion4": "Bard",
    "enermy_id4": "김말모"
  },
  "5194029553": {
    "gameID": "5194029553",
    "gameResult": "lose",
    "GameType": "Ranked Solo",
    "gameTime_string": "2021-05-14 02:19:17",
    "GameLength": "22m 13s",
    "kill": "7",
    "Death": "3",
    "Assist": "6",
    "KDARatio": "4.33:1",
    "Badge1": "ACE",
    "Badge2": "empty",
    "champion": "Lee Sin",
    "Tier_Average": "Diamond 1",
    "Control_Ward": "empty",
    "teammate_champion0": "Trundle",
    "teammate_id0": "6월 호랑이",
    "teammate_champion1": "Diana",
    "teammate_id1": "Px8",
    "teammate_champion2": "Yasuo",
    "teammate_id2": "교생관양",
    "teammate_champion3": "Kalista",
    "teammate_id3": "2598491461805184",
    "teammate_champion4": "Alistar",
    "teammate_id4": "Detiny",
    "enermy_champion0": "Sett",
    "enermy_id0": "귀염뾰짝 전지용",
    "enermy_champion1": "Lee Sin",
    "enermy_id1": "Ma1ibu night",
    "enermy_champion2": "Syndra",
    "enermy_id2": "jltdtimy",
    "enermy_champion3": "Jinx",
    "enermy_id3": "GoIden Bell",
    "enermy_champion4": "Rakan",
    "enermy_id4": "논리왕전기1"
  },
  "5193965481": {
    "gameID": "5193965481",
    "gameResult": "lose",
    "GameType": "Ranked Solo",
    "gameTime_string": "2021-05-14 01:45:57",
    "GameLength": "27m 2s",
    "kill": "5",
    "Death": "8",
    "Assist": "3",
    "KDARatio": "1.00:1",
    "Badge1": "empty",
    "Badge2": "empty",
    "champion": "Kai'Sa",
    "Tier_Average": "Master",
    "Control_Ward": "empty",
    "teammate_champion0": "Lucian",
    "teammate_id0": "leehiiii",
    "teammate_champion1": "Rumble",
    "teammate_id1": "haoyunsenming",
    "teammate_champion2": "Zed",
    "teammate_id2": "굼 룬",
    "teammate_champion3": "Jhin",
    "teammate_id3": "채팅안해볼게요",
    "teammate_champion4": "Alistar",
    "teammate_id4": "2021Worlds0173",
    "enermy_champion0": "Jayce",
    "enermy_id0": "분노 증오 환멸",
    "enermy_champion1": "Skarner",
    "enermy_id1": "시골러",
    "enermy_champion2": "Akali",
    "enermy_id2": "흐물흐물 파테",
    "enermy_champion3": "Kai'Sa",
    "enermy_id3": "Ma1ibu night",
    "enermy_champion4": "Rakan",
    "enermy_id4": "논리왕전기1"
  },
  "5193786407": {
    "gameID": "5193786407",
    "gameResult": "win",
    "GameType": "Ranked Solo",
    "gameTime_string": "2021-05-14 00:49:52",
    "GameLength": "30m 44s",
    "kill": "11",
    "Death": "6",
    "Assist": "10",
    "KDARatio": "3.50:1",
    "Badge1": "Triple Kill",
    "Badge2": "MVP",
    "champion": "Viego",
    "Tier_Average": "Diamond 1",
    "Control_Ward": "empty",
    "teammate_champion0": "Garen",
    "teammate_id0": "GarenK1ng",
    "teammate_champion1": "Viego",
    "teammate_id1": "Ma1ibu night",
    "teammate_champion2": "Katarina",
    "teammate_id2": "애니보는게죄냐",
    "teammate_champion3": "Kai'Sa",
    "teammate_id3": "iuiuiuiuiuiuiuu",
    "teammate_champion4": "Pyke",
    "teammate_id4": "pyke k1ng",
    "enermy_champion0": "Gwen",
    "enermy_id0": "XYXXXXXY",
    "enermy_champion1": "Lee Sin",
    "enermy_id1": "Jx Wxx Hx",
    "enermy_champion2": "Twisted Fate",
    "enermy_id2": "Gen G Ophelia",
    "enermy_champion3": "Lucian",
    "enermy_id3": "연애포기 삐약이",
    "enermy_champion4": "Galio",
    "enermy_id4": "XUBINGJIE"
  },
  "5193538734": {
    "gameID": "5193538734",
    "gameResult": "win",
    "GameType": "Ranked Solo",
    "gameTime_string": "2021-05-14 00:04:26",
    "GameLength": "27m 54s",
    "kill": "13",
    "Death": "7",
    "Assist": "19",
    "KDARatio": "4.57:1",
    "Badge1": "Double Kill",
    "Badge2": "empty",
    "champion": "Rumble",
    "Tier_Average": "Master",
    "Control_Ward": "empty",
    "teammate_champion0": "Jayce",
    "teammate_id0": "HLE Mask",
    "teammate_champion1": "Rumble",
    "teammate_id1": "Ma1ibu night",
    "teammate_champion2": "Yasuo",
    "teammate_id2": "악귀연무",
    "teammate_champion3": "Jinx",
    "teammate_id3": "iuiuiuiuiuiuiuu",
    "teammate_champion4": "Leona",
    "teammate_id4": "placeb0",
    "enermy_champion0": "Sett",
    "enermy_id0": "거북이사건",
    "enermy_champion1": "Kindred",
    "enermy_id1": "성장방해하지마요",
    "enermy_champion2": "Aatrox",
    "enermy_id2": "여 길 떠 나1",
    "enermy_champion3": "Draven",
    "enermy_id3": "중드장",
    "enermy_champion4": "Alistar",
    "enermy_id4": "adventure hunter"
  },
  "5192124335": {
    "gameID": "5192124335",
    "gameResult": "win",
    "GameType": "Ranked Solo",
    "gameTime_string": "2021-05-13 03:52:38",
    "GameLength": "22m 3s",
    "kill": "12",
    "Death": "4",
    "Assist": "9",
    "KDARatio": "5.25:1",
    "Badge1": "Quadra Kill",
    "Badge2": "empty",
    "champion": "Kha'Zix",
    "Tier_Average": "Diamond 1",
    "Control_Ward": "empty",
    "teammate_champion0": "Lucian",
    "teammate_id0": "버 돌",
    "teammate_champion1": "Kha'Zix",
    "teammate_id1": "Ma1ibu night",
    "teammate_champion2": "Galio",
    "teammate_id2": "이리스",
    "teammate_champion3": "Jinx",
    "teammate_id3": "그럴 쑤 잇지",
    "teammate_champion4": "Alistar",
    "teammate_id4": "bot game can win",
    "enermy_champion0": "Tristana",
    "enermy_id0": "Rascal",
    "enermy_champion1": "Kindred",
    "enermy_id1": "ning yue ru feng",
    "enermy_champion2": "Ryze",
    "enermy_id2": "류병준입니다",
    "enermy_champion3": "Ezreal",
    "enermy_id3": "Fatty",
    "enermy_champion4": "Karma",
    "enermy_id4": "ISFP그자체"
  },
  "5192072616": {
    "gameID": "5192072616",
    "gameResult": "win",
    "GameType": "Ranked Solo",
    "gameTime_string": "2021-05-13 03:16:19",
    "GameLength": "22m 44s",
    "kill": "5",
    "Death": "5",
    "Assist": "16",
    "KDARatio": "4.20:1",
    "Badge1": "empty",
    "Badge2": "empty",
    "champion": "Diana",
    "Tier_Average": "Diamond 2",
    "Control_Ward": "empty",
    "teammate_champion0": "Jayce",
    "teammate_id0": "버 돌",
    "teammate_champion1": "Diana",
    "teammate_id1": "Ma1ibu night",
    "teammate_champion2": "Yone",
    "teammate_id2": "CORSA Mode",
    "teammate_champion3": "Tristana",
    "teammate_id3": "SnimxPuppy",
    "teammate_champion4": "Alistar",
    "teammate_id4": "편하게 하다",
    "enermy_champion0": "Kled",
    "enermy_id0": "2672359476569216",
    "enermy_champion1": "Kindred",
    "enermy_id1": "Taehyoung",
    "enermy_champion2": "Akali",
    "enermy_id2": "그럴 쑤 잇지",
    "enermy_champion3": "Aphelios",
    "enermy_id3": "2598491461805184",
    "enermy_champion4": "Thresh",
    "enermy_id4": "Detiny"
  },
  "5192008882": {
    "gameID": "5192008882",
    "gameResult": "lose",
    "GameType": "Ranked Solo",
    "gameTime_string": "2021-05-13 02:37:08",
    "GameLength": "27m 2s",
    "kill": "7",
    "Death": "4",
    "Assist": "5",
    "KDARatio": "3.00:1",
    "Badge1": "Double Kill",
    "Badge2": "ACE",
    "champion": "Diana",
    "Tier_Average": "Diamond 1",
    "Control_Ward": "empty",
    "teammate_champion0": "Irelia",
    "teammate_id0": "버 돌",
    "teammate_champion1": "Diana",
    "teammate_id1": "Ma1ibu night",
    "teammate_champion2": "Sylas",
    "teammate_id2": "MIDMINE",
    "teammate_champion3": "Miss Fortune",
    "teammate_id3": "HLE ChungSin",
    "teammate_champion4": "Senna",
    "teammate_id4": "ISFP그자체",
    "enermy_champion0": "Lee Sin",
    "enermy_id0": "zhendebuzhidao",
    "enermy_champion1": "Morgana",
    "enermy_id1": "Iuckgame9",
    "enermy_champion2": "Akali",
    "enermy_id2": " Gen G Bdd",
    "enermy_champion3": "Jinx",
    "enermy_id3": "응애예티원딜",
    "enermy_champion4": "Alistar",
    "enermy_id4": "363363363"
  },
  "5192032808": {
    "gameID": "5192032808",
    "gameResult": "win",
    "GameType": "Ranked Solo",
    "gameTime_string": "2021-05-13 01:32:58",
    "GameLength": "18m 50s",
    "kill": "7",
    "Death": "2",
    "Assist": "14",
    "KDARatio": "10.50:1",
    "Badge1": "MVP",
    "Badge2": "empty",
    "champion": "Lillia",
    "Tier_Average": "Diamond 1",
    "Control_Ward": "empty",
    "teammate_champion0": "Renekton",
    "teammate_id0": "버 돌",
    "teammate_champion1": "Lillia",
    "teammate_id1": "Ma1ibu night",
    "teammate_champion2": "Xerath",
    "teammate_id2": "끝나고 싸우셈",
    "teammate_champion3": "Kai'Sa",
    "teammate_id3": "산중호걸 호랑",
    "teammate_champion4": "Leona",
    "teammate_id4": "Changer1",
    "enermy_champion0": "Gwen",
    "enermy_id0": "96350652del",
    "enermy_champion1": "Lee Sin",
    "enermy_id1": "늘 봄은온다",
    "enermy_champion2": "Anivia",
    "enermy_id2": "팝스타알",
    "enermy_champion3": "Samira",
    "enermy_id3": "Dreams1",
    "enermy_champion4": "Alistar",
    "enermy_id4": "논리왕전기1"
  },
  "5191907597": {
    "gameID": "5191907597",
    "gameResult": "win",
    "GameType": "Ranked Solo",
    "gameTime_string": "2021-05-13 01:03:06",
    "GameLength": "29m 15s",
    "kill": "5",
    "Death": "7",
    "Assist": "7",
    "KDARatio": "1.71:1",
    "Badge1": "Double Kill",
    "Badge2": "empty",
    "champion": "Camille",
    "Tier_Average": "Diamond 1",
    "Control_Ward": "empty",
    "teammate_champion0": "Gnar",
    "teammate_id0": "버 돌",
    "teammate_champion1": "Camille",
    "teammate_id1": "Ma1ibu night",
    "teammate_champion2": "Azir",
    "teammate_id2": "악희샹어",
    "teammate_champion3": "Kai'Sa",
    "teammate_id3": "억울해 나",
    "teammate_champion4": "Nautilus",
    "teammate_id4": "iuiuiuiuiuiuiuu",
    "enermy_champion0": "Rumble",
    "enermy_id0": "모두모두항복하걸",
    "enermy_champion1": "Nocturne",
    "enermy_id1": "15gggggggggg",
    "enermy_champion2": "Zoe",
    "enermy_id2": "NS GGori",
    "enermy_champion3": "Jinx",
    "enermy_id3": "lilililiililill",
    "enermy_champion4": "Lulu",
    "enermy_id4": "ISFP그자체"
  },
  "5189959216": {
    "gameID": "5189959216",
    "gameResult": "lose",
    "GameType": "Ranked Solo",
    "gameTime_string": "2021-05-12 02:40:04",
    "GameLength": "18m 26s",
    "kill": "2",
    "Death": "4",
    "Assist": "3",
    "KDARatio": "1.25:1",
    "Badge1": "ACE",
    "Badge2": "empty",
    "champion": "Viego",
    "Tier_Average": "Diamond 1",
    "Control_Ward": "empty",
    "teammate_champion0": "Pantheon",
    "teammate_id0": "1147512",
    "teammate_champion1": "Nidalee",
    "teammate_id1": "경고했을 텐데",
    "teammate_champion2": "Sylas",
    "teammate_id2": "hu da shuaishuai",
    "teammate_champion3": "Xayah",
    "teammate_id3": "xiaochou1",
    "teammate_champion4": "Karma",
    "teammate_id4": "Happy Cats",
    "enermy_champion0": "Kennen",
    "enermy_id0": "Innocent crown",
    "enermy_champion1": "Viego",
    "enermy_id1": "Ma1ibu night",
    "enermy_champion2": "Zoe",
    "enermy_id2": "God Rui",
    "enermy_champion3": "Aphelios",
    "enermy_id3": "ggttlckp127",
    "enermy_champion4": "Leona",
    "enermy_id4": "소쫑우"
  },
  "5188265252": {
    "gameID": "5188265252",
    "gameResult": "win",
    "GameType": "Ranked Solo",
    "gameTime_string": "2021-05-11 04:10:55",
    "GameLength": "18m 38s",
    "kill": "7",
    "Death": "0",
    "Assist": "9",
    "KDARatio": "Perfect",
    "Badge1": "MVP",
    "Badge2": "empty",
    "champion": "Viego",
    "Tier_Average": "Diamond 3",
    "Control_Ward": "empty",
    "teammate_champion0": "Dr. Mundo",
    "teammate_id0": "무지성탑입니다꼬우면오세요",
    "teammate_champion1": "Lee Sin",
    "teammate_id1": "그냥 벽 youtube",
    "teammate_champion2": "Anivia",
    "teammate_id2": "Anivia xxx",
    "teammate_champion3": "Kalista",
    "teammate_id3": "54454488888",
    "teammate_champion4": "Rell",
    "teammate_id4": "SongGoon",
    "enermy_champion0": "Gwen",
    "enermy_id0": "버 돌",
    "enermy_champion1": "Viego",
    "enermy_id1": "Ma1ibu night",
    "enermy_champion2": "Sylas",
    "enermy_id2": "찌릿찌릿 정상수",
    "enermy_champion3": "Jinx",
    "enermy_id3": "떠나고싶엉",
    "enermy_champion4": "Lulu",
    "enermy_id4": "29080985del"
  },
  "5188177212": {
    "gameID": "5188177212",
    "gameResult": "win",
    "GameType": "Ranked Solo",
    "gameTime_string": "2021-05-11 02:42:26",
    "GameLength": "23m 48s",
    "kill": "6",
    "Death": "2",
    "Assist": "6",
    "KDARatio": "6.00:1",
    "Badge1": "MVP",
    "Badge2": "empty",
    "champion": "Evelynn",
    "Tier_Average": "Diamond 2",
    "Control_Ward": "empty",
    "teammate_champion0": "Lee Sin",
    "teammate_id0": "버 돌",
    "teammate_champion1": "Evelynn",
    "teammate_id1": "Ma1ibu night",
    "teammate_champion2": "Irelia",
    "teammate_id2": "2704844696217248",
    "teammate_champion3": "Caitlyn",
    "teammate_id3": "chongxinkaishiI",
    "teammate_champion4": "Lux",
    "teammate_id4": "32423489del",
    "enermy_champion0": "Fiora",
    "enermy_id0": "asdfgasdf",
    "enermy_champion1": "Rumble",
    "enermy_id1": "아이러니하구만",
    "enermy_champion2": "Pantheon",
    "enermy_id2": "54740131del",
    "enermy_champion3": "Jinx",
    "enermy_id3": "Vayn",
    "enermy_champion4": "Thresh",
    "enermy_id4": "2706926766229408"
  },
  "5188124196": {
    "gameID": "5188124196",
    "gameResult": "win",
    "GameType": "Ranked Solo",
    "gameTime_string": "2021-05-11 01:56:59",
    "GameLength": "27m 20s",
    "kill": "7",
    "Death": "5",
    "Assist": "10",
    "KDARatio": "3.40:1",
    "Badge1": "MVP",
    "Badge2": "empty",
    "champion": "Diana",
    "Tier_Average": "Diamond 2",
    "Control_Ward": "empty",
    "teammate_champion0": "Tryndamere",
    "teammate_id0": "장트린다미어",
    "teammate_champion1": "Morgana",
    "teammate_id1": "0도0",
    "teammate_champion2": "Viktor",
    "teammate_id2": "카시버프좀요",
    "teammate_champion3": "Samira",
    "teammate_id3": "숏레그 먼치킨",
    "teammate_champion4": "Alistar",
    "teammate_id4": "Helperrrrrrr",
    "enermy_champion0": "Lee Sin",
    "enermy_id0": "버 돌",
    "enermy_champion1": "Diana",
    "enermy_id1": "Ma1ibu night",
    "enermy_champion2": "Qiyana",
    "enermy_id2": "담배냄새싫어요",
    "enermy_champion3": "Kai'Sa",
    "enermy_id3": "민준가",
    "enermy_champion4": "Rell",
    "enermy_id4": "BewhY77"
  },
  "5187888255": {
    "gameID": "5187888255",
    "gameResult": "win",
    "GameType": "Ranked Solo",
    "gameTime_string": "2021-05-11 01:11:51",
    "GameLength": "37m 17s",
    "kill": "8",
    "Death": "6",
    "Assist": "19",
    "KDARatio": "4.50:1",
    "Badge1": "Triple Kill",
    "Badge2": "MVP",
    "champion": "Viego",
    "Tier_Average": "Diamond 2",
    "Control_Ward": "empty",
    "teammate_champion0": "Qiyana",
    "teammate_id0": "눈부시게빛날테니",
    "teammate_champion1": "Lee Sin",
    "teammate_id1": "후천개벽",
    "teammate_champion2": "Kennen",
    "teammate_id2": "고나호",
    "teammate_champion3": "Varus",
    "teammate_id3": "잇몸천사 황재욱",
    "teammate_champion4": "Rell",
    "teammate_id4": "BewhY77",
    "enermy_champion0": "Gwen",
    "enermy_id0": "버 돌",
    "enermy_champion1": "Viego",
    "enermy_id1": "Ma1ibu night",
    "enermy_champion2": "Renekton",
    "enermy_id2": "1Tier Nangyee",
    "enermy_champion3": "Kai'Sa",
    "enermy_id3": "shuolezaIjian1",
    "enermy_champion4": "Blitzcrank",
    "enermy_id4": "우리  항상 웃자"
  }
}